{
    "1.0": {
        "T_START": 1746389791.871488,
        "T_END": 1746389911.871488,
        "warmup_creates_submitted": 15,
        "warmup_deletes_submitted": 15,
        "measurement_creates_submitted": 60,
        "measurement_deletes_submitted": 60,
        "target_pool_size": 100
    },
    "2.0": {
        "T_START": 1746390001.903231,
        "T_END": 1746390121.903231,
        "warmup_creates_submitted": 30,
        "warmup_deletes_submitted": 30,
        "measurement_creates_submitted": 120,
        "measurement_deletes_submitted": 120,
        "target_pool_size": 100
    },
    "4.0": {
        "T_START": 1746390213.235552,
        "T_END": 1746390333.235552,
        "warmup_creates_submitted": 60,
        "warmup_deletes_submitted": 60,
        "measurement_creates_submitted": 240,
        "measurement_deletes_submitted": 240,
        "target_pool_size": 100
    },
    "8.0": {
        "T_START": 1746390423.519586,
        "T_END": 1746390543.519586,
        "warmup_creates_submitted": 120,
        "warmup_deletes_submitted": 120,
        "measurement_creates_submitted": 480,
        "measurement_deletes_submitted": 480,
        "target_pool_size": 100
    }
}